polyply/__init__.py
polyply/data/__init__.py
polyply/data/2016H66/chiral_links.ff
polyply/data/2016H66/citation.bib
polyply/data/2016H66/polyether_blocks.ff
polyply/data/2016H66/polyether_links.ff
polyply/data/2016H66/polyether_polyvinyl_links.ff
polyply/data/2016H66/polyvinyl_blocks.ff
polyply/data/2016H66/polyvinyl_links.ff
polyply/data/2016H66/terminal_blocks.ff
polyply/data/gromos53A6/Hter.ff
polyply/data/gromos53A6/P3HT.gromos.53A6.ff
polyply/data/gromos53A6/citations.bib
polyply/data/gromos53A6/links.ff
polyply/data/ibi_cgm3/PTMA.cgm3.ibi.ff
polyply/data/ibi_cgm3/citations.bib
polyply/data/ibi_gbcg/PTMA.gbno2.ibi.ff
polyply/data/ibi_gbcg/citations.bib
polyply/data/martini2/DNA_M2.ff
polyply/data/martini2/P3HT.martini.2.itp
polyply/data/martini2/PDADMA.martini.2.itp
polyply/data/martini2/PE.martini.2.itp
polyply/data/martini2/PEO.martini.2.itp
polyply/data/martini2/PP.martini.2.itp
polyply/data/martini2/PS.martini.2.itp
polyply/data/martini2/PSS.martini.2.itp
polyply/data/martini2/citations.bib
polyply/data/martini2/links.ff
polyply/data/martini3/P3HT.martini3.ff
polyply/data/martini3/PDMS.martini3.ff
polyply/data/martini3/PE.martini3.ff
polyply/data/martini3/PEL_link.ff
polyply/data/martini3/PEO.martini3.ff
polyply/data/martini3/PMA.martini3.ff
polyply/data/martini3/PMMA.martini3.ff
polyply/data/martini3/PPE.martini3.ff
polyply/data/martini3/PS.martini3.ff
polyply/data/martini3/PSS.martini3.ff
polyply/data/martini3/PS_PEO_link.ff
polyply/data/martini3/PTMA.martini3.ff
polyply/data/martini3/PVA.martini3.ff
polyply/data/martini3/aminoacids.ff
polyply/data/martini3/cellulose.martini3.ff
polyply/data/martini3/citations.bib
polyply/data/martini3/dextran.martini3.ff
polyply/data/martini3/modifications.ff
polyply/data/martini3-go/aminoacids.ff
polyply/data/martini3-go/citations.bib
polyply/data/martini3-go/modifications.ff
polyply/data/martini3_beta/PEO.martini.3.itp
polyply/data/martini3_beta/citations.bib
polyply/data/oplsaaLigParGen/CH3.ff
polyply-1.8.0.dist-info/licenses/AUTHORS
polyply-1.8.0.dist-info/licenses/LICENSE
polyply-1.8.0.dist-info/METADATA
polyply-1.8.0.dist-info/WHEEL
polyply-1.8.0.dist-info/pbr.json
polyply-1.8.0.dist-info/top_level.txt
polyply-1.8.0.dist-info/RECORD
