Metadata-Version: 2.4
Name: polyply
Version: 1.8.0
Home-page: https://github.com/marrink-lab/polyply_1.0
Author: Fabian Grunewald
Author-email: f.grunewald@rug.nl
License: Apache 2.0
Keywords: molecular dynamics charmm gromos martini polymers
Classifier: Development Status :: 5 - Production/Stable
Classifier: Environment :: Console
Classifier: Intended Audience :: Developers
Classifier: Intended Audience :: Science/Research
Classifier: License :: OSI Approved :: Apache Software License
Classifier: Operating System :: OS Independent
Classifier: Programming Language :: Python :: 3
Classifier: Programming Language :: Python :: 3.5
Classifier: Programming Language :: Python :: 3.6
Classifier: Programming Language :: Python :: 3.7
Classifier: Programming Language :: Python :: 3.8
Classifier: Topic :: Scientific/Engineering :: Bio-Informatics
Classifier: Topic :: Scientific/Engineering :: Chemistry
License-File: LICENSE
License-File: AUTHORS
Requires-Dist: pbr
Requires-Dist: numpy
Requires-Dist: decorator==4.4.2
Requires-Dist: networkx>=2.0
Requires-Dist: vermouth>=0.14.0
Requires-Dist: scipy>=1.6.0
Requires-Dist: tqdm
Dynamic: author
Dynamic: author-email
Dynamic: classifier
Dynamic: description
Dynamic: description-content-type
Dynamic: keywords
Dynamic: license
Dynamic: license-file
